flex_function/__init__.py
flex_function/gen_function.py
flex_function-0.0.4.dist-info/METADATA
flex_function-0.0.4.dist-info/WHEEL
flex_function-0.0.4.dist-info/licenses/LICENSE
flex_function-0.0.4.dist-info/RECORD
