Metadata-Version: 2.4
Name: flex_function
Version: 0.0.4
Summary: Python access to Genra's Flexfunction.
Author-email: Maxwell Laibson <maxlaibson@gmail.com>
License-Expression: MIT
License-File: LICENSE
Classifier: Operating System :: OS Independent
Classifier: Programming Language :: Python :: 3
Requires-Python: >=3.8
